{
  "content": ":\n\n(¬1) أي: عند ازدحام الغرماء، كما هي العبارة في \"نهاية المطلب\" (6/ 282)، لكن وقعت فيه هذه الجمل بالإثبات؛ أي: \"على أن تتوثق به، أو على أن يباع ... ، أو تقدم ... \".\n\n\n            <div class='pageno-container'>\n                <a class='pageno' href='#' id='v04p007'> Vol. 04, p. 007</a>\n            </div>\n            :\n\n(¬1) في \"ل\": \"الدين\".\n\n\n            <div class='pageno-container'>\n                <a class='pageno' href='#' id='v04p009'> Vol. 04, p. 009</a>\n            </div>\n            :\n\n(¬1) في \"ل\": \"التشطر\".\n\n\n            <div class='pageno-container'>\n                <a class='pageno' href='#' id='v04p010'> Vol. 04, p. 010</a>\n            </div>\n            :\n\n(¬1) في \"ل\": \"تخير\".\n\n\n            <div class='pageno-container'>\n                <a class='pageno' href='#' id='v04p014'> Vol. 04, p. 014</a>\n            </div>\n            :\n\n(¬1) في \"م\": \"لأجل\".\n\n\n            <div class='pageno-container'>\n                <a class='pageno' href='#' id='v04p015'> Vol. 04, p. 015</a>\n            </div>\n            :\n\n(¬1) أي: انطلاق الحجر؛ أي: لو انفك الحجر عنه كان له القلع بعلة انطلاق الحجر. انظر: \"نهاية المطلب\" (6/ 330).\n\n\n            <div class='pageno-container'>\n                <a class='pageno' href='#' id='v04p016'> Vol. 04, p. 016</a>\n            </div>\n            :\n\n(¬1) في \"ل\": \"وجد\".\n(¬2) في \"ل\": \"في الجارية\".\n(¬3) في \"ل\": \"ففي الثمر وجهان <span id='ms1688'></span>\".\n\n\n            <div class='pageno-container'>\n                <a class='pageno' href='#' id='v04p018'> Vol. 04, p. 018</a>\n            </div>\n            :\n\n(¬1) ما بين معكوفتين من \"نهاية المطلب\" (6/ 336).\n\n\n            <div class='pageno-container'>\n                <a class='pageno' href='#' id='v04p021'> Vol. 04, p. 021</a>\n            </div>\n            :\n\n(¬1) في \"ل\": \"وهذا\".\n\n\n            <div class='pageno-container'>\n                <a class='pageno' href='#' id='v04p023'> Vol. 04, p. 023</a>\n            </div>\n            :\n\n(¬1) في \"م\": \"أدنى\"، والمثبت موافق لما في \"نهاية المطلب\" (6/ 352).\n\n\n            <div class='pageno-container'>\n                <a class='pageno' href='#' id='v04p025'> Vol. 04, p. 025</a>\n            </div>\n            :\n\n(¬1) وقع قبلها في هامش \"م\": \"إذا\"، ويقابل هذه العبارة في \"نهاية المطلب\" (6/ 361): \"حبس البائع المبيع -إن رأينا له الحبس- حتى يقبض الثمن\".\n\n\n            <div class='pageno-container'>\n                <a class='pageno' href='#' id='v04p027'> Vol. 04, p. 027</a>\n            </div>\n            :\n\n(¬1) في \"ل\": \"بالاتفاق\".\n\n\n            <div class='pageno-container'>\n                <a class='pageno' href='#' id='v04p029'> Vol. 04, p. 029</a>\n            </div>\n            :\n\n(¬1) في \"ل\": \"وقيمته على السلامة\".\n(¬2) في \"ل\": \"فيما زاد على الثلث\".\n\n\n            <div class='pageno-container'>\n                <a class='pageno' href='#' id='v04p031'> Vol. 04, p. 031</a>\n            </div>\n            :\n\n(¬1) في \"م\": \"فاختص\".\n\n\n            <div class='pageno-container'>\n                <a class='pageno' href='#' id='v04p034'> Vol. 04, p. 034</a>\n            </div>\n            :\n\n(¬1) أي: الحجر.\n\n\n            <div class='pageno-container'>\n                <a class='pageno' href='#' id='v04p035'> Vol. 04, p. 035</a>\n            </div>\n            :\n\n(¬1) أي: البداية بالتسليم.\n\n\n            <div class='pageno-container'>\n                <a class='pageno' href='#' id='v04p037'> Vol. 04, p. 037</a>\n            </div>\n            :\n\n(¬1) أي: إلى انطلاق الحجر عنه. انظر: \"نهاية المطلب\" (6/ 398).\n(¬2) في \"ل\": \"وكذلك\".\n\n\n            <div class='pageno-container'>\n                <a class='pageno' href='#' id='v04p038'> Vol. 04, p. 038</a>\n            </div>\n            :\n\n(¬1) في \"ل\": \"وكذلك\".\n\n\n            <div class='pageno-container'>\n                <a class='pageno' href='#' id='v04p039'> Vol. 04, p. 039</a>\n            </div>\n            :\n\n(¬1) في \"ل\": \"وأبعد من قال: الحصص المؤجلة على الحلول\".\n\n\n            <div class='pageno-container'>\n                <a class='pageno' href='#' id='v04p041'> Vol. 04, p. 041</a>\n            </div>\n            :\n\n(¬1) الدست كفلس: ما يلبسه الإنسان من الثياب ويكفيه لتردده في حوائجه. انظر: \"المصباح المنير\" للفيومي (مادة: دست).\n(¬2) لعله الذي يعمل في إيقاد الأتون -وهو الموقد- والقيام عليه.\n(¬3) زيادة من \"نهاية المطلب\" (6/ 411).\n\n\n            <div class='pageno-container'>\n                <a class='pageno' href='#' id='v04p049'> Vol. 04, p. 049</a>\n            </div>\n            :\n\n(¬1) في \"ل\": \"يبنى\".\n\n\n            <div class='pageno-container'>\n                <a class='pageno' href='#' id='v04p054'> Vol. 04, p. 054</a>\n            </div>\n            :\n\n(¬1) في \"ل\": \"السنة الثامنة\".\n\n\n            <div class='pageno-container'>\n                <a class='pageno' href='#' id='v04p055'> Vol. 04, p. 055</a>\n            </div>\n            :\n\n(¬1) أي: إذا اعتقبا. انظر: \"نهاية المطلب\" (6/ 437).\n\n\n            <div class='pageno-container'>\n                <a class='pageno' href='#' id='v04p066'> Vol. 04, p. 066</a>\n            </div>\n            :\n\n(¬1) في \"م\": \"أصالح\".\n\n\n            <div class='pageno-container'>\n                <a class='pageno' href='#' id='v04p069'> Vol. 04, p. 069</a>\n            </div>\n            :\n\n(¬1) في \"ل\": \"من حقوقه\"، وفي \"نهاية المطلب\" (6/ 464): \"من حقوق المالك\".\n\n\n            <div class='pageno-container'>\n                <a class='pageno' href='#' id='v04p070'> Vol. 04, p. 070</a>\n            </div>\n            :\n\n(¬1) جمع الكنيسة، وهو هنا: شبه الهودج: يغرس في المحمل أو في الرحل قضبان، ويلقى عليه ثوب يستظل به الراكب ويستتر به. انظر: \"المصباح المنير\" للفيومي (مادة: كنس).\n\n\n            <div class='pageno-container'>\n                <a class='pageno' href='#' id='v04p071'> Vol. 04, p. 071</a>\n            </div>\n            :\n\n(¬1) بنيات الطرق: هي الطرق الصغار تنشعب من الجادة. انظر: \"لسان العرب\" لابن منظور (مادة: بني).\n\n\n            <div class='pageno-container'>\n                <a class='pageno' href='#' id='v04p072'> Vol. 04, p. 072</a>\n            </div>\n            :\n\n(¬1) في \"ل\": \"الوجهان\".\n(¬2) في \"ل\": \"أهل الدرب\".\n\n\n            <div class='pageno-container'>\n                <a class='pageno' href='#' id='v04p073'> Vol. 04, p. 073</a>\n            </div>\n            :\n\n(¬1) في هامش \"م\": \"صوابه: ولم يصدق في الجهة\".\n\n\n            <div class='pageno-container'>\n                <a class='pageno' href='#' id='v04p074'> Vol. 04, p. 074</a>\n            </div>\n            :\n\n(¬1) في \"ل\": \"رجع إلى\".\n\n\n            <div class='pageno-container'>\n                <a class='pageno' href='#' id='v04p076'> Vol. 04, p. 076</a>\n            </div>\n            :\n\n(¬1) الأزج: بناء مستطيل مقوس السقف. انظر: \"المعجم الوسيط\" (مادة: أزج).\n\n\n            <div class='pageno-container'>\n                <a class='pageno' href='#' id='v04p077'> Vol. 04, p. 077</a>\n            </div>\n            :\n\n(¬1) أي: تضبيب الإناء بالفضة.\n\n\n            <div class='pageno-container'>\n                <a class='pageno' href='#' id='v04p081'> Vol. 04, p. 081</a>\n            </div>\n            :\n\n(¬1) أي: إن كان بناء سقف السفل ممكنا بعد بناء سقف العلو بأن يفرض سقف عال ثم يفرض سقف دونه، بأن تدرج رؤوس الجذوع في وسط الجدار وينظم عليها السقف. انظر: \"نهاية المطلب\" (6/ 492).\n\n\n            <div class='pageno-container'>\n                <a class='pageno' href='#' id='v04p085'> Vol. 04, p. 085</a>\n            </div>\n            :\n\n(¬1) في \"ل\": \"وجهان\".\n\n\n            <div class='pageno-container'>\n                <a class='pageno' href='#' id='v04p103'> Vol. 04, p. 103</a>\n            </div>\n            :\n\n(¬1) في \"نهاية المطلب\" (7/ 5): \"تطويل الزمان\".\n\n\n            <div class='pageno-container'>\n                <a class='pageno' href='#' id='v04p105'> Vol. 04, p. 105</a>\n            </div>\n            :\n\n(¬1) في \"ل\": \"وإن قال أديت ولم أشهد\"، والمثبت موافق لما في \"نهاية المطلب\" (7/ 7).\n\n\n            <div class='pageno-container'>\n                <a class='pageno' href='#' id='v04p108'> Vol. 04, p. 108</a>\n            </div>\n            :\n\n(¬1) أي: \"أبرأ الأصيل\".\n\n\n            <div class='pageno-container'>\n                <a class='pageno' href='#' id='v04p113'> Vol. 04, p. 113</a>\n            </div>\n            :\n\n(¬1) في \"نهاية المطلب\" (7/ 12): \"الأصل\".\n\n\n            <div class='pageno-container'>\n                <a class='pageno' href='#' id='v04p134'> Vol. 04, p. 134</a>\n            </div>\n            :\n\n(¬1) الفيلج: وزان زينب: ما يتخذ منه القز، وهو معرب. انظر: \"المصباح المنير\" للفيومي (مادة: فلج).\n\n\n            <div class='pageno-container'>\n                <a class='pageno' href='#' id='v04p137'> Vol. 04, p. 137</a>\n            </div>\n            :\n\n(¬1) \"الشيخ\" هنا هو \"الشيخ أبو علي\" كما صرح <span id='ms1689'></span> بذلك الرافعي، وإذا قيل: \"الشيخ أبو علي\"، فهو السنجي. انظر: \"الشرح الكبير\" بهامش \"المجموع\" (10/ 450).\n\n\n            <div class='pageno-container'>\n                <a class='pageno' href='#' id='v04p143'> Vol. 04, p. 143</a>\n            </div>\n            :\n\n(¬1) في \"ل\": وإن أجاز.\n\n\n            <div class='pageno-container'>\n                <a class='pageno' href='#' id='v04p151'> Vol. 04, p. 151</a>\n            </div>\n            :\n\n(¬1) في \"ل\": \"فأنكره\".\n\n\n            <div class='pageno-container'>\n                <a class='pageno' href='#' id='v04p158'> Vol. 04, p. 158</a>\n            </div>\n            :\n\n(¬1) في \"ل\": \"تزويج\".\n\n\n            <div class='pageno-container'>\n                <a class='pageno' href='#' id='v04p161'> Vol. 04, p. 161</a>\n            </div>\n            :\n\n(¬1) في \"ل\": \"فهل يخيره؟ قولان\".\n\n\n            <div class='pageno-container'>\n                <a class='pageno' href='#' id='v04p163'> Vol. 04, p. 163</a>\n            </div>\n            :\n\n(¬1) في النسخ: \"البائع\"، والصواب المثبت.\n\n\n            <div class='pageno-container'>\n                <a class='pageno' href='#' id='v04p164'> Vol. 04, p. 164</a>\n            </div>\n            :\n\n(¬1) في \"م\": \"رجع\"، وكذا في مطبوع \"نهاية المطلب\" (7/ 50).\n\n\n            <div class='pageno-container'>\n                <a class='pageno' href='#' id='v04p166'> Vol. 04, p. 166</a>\n            </div>\n            :\n\n(¬1) في \"ل\": \"والسندي صح إن قدر الثمن\".\n\n\n            <div class='pageno-container'>\n                <a class='pageno' href='#' id='v04p170'> Vol. 04, p. 170</a>\n            </div>\n            :\n\n(¬1) في \"ل\": \"بالردة\"، وفي \"نهاية المطلب\" (7/ 54): \"بردة الوكيل\".\n\n\n            <div class='pageno-container'>\n                <a class='pageno' href='#' id='v04p174'> Vol. 04, p. 174</a>\n            </div>\n            :\n\n(¬1) في \"ل\": على أصح الوجهين.\n(¬2) أي: ولا بعد رفع الحجر عنه.\n\n\n            <div class='pageno-container'>\n                <a class='pageno' href='#' id='v04p175'> Vol. 04, p. 175</a>\n            </div>\n            :\n\n(¬1) في \"ل\": \"أو باتفاق\".\n\n\n            <div class='pageno-container'>\n                <a class='pageno' href='#' id='v04p180'> Vol. 04, p. 180</a>\n            </div>\n            :\n\n(¬1) في \"ل\": \"يطلق\".\n\n\n            <div class='pageno-container'>\n                <a class='pageno' href='#' id='v04p184'> Vol. 04, p. 184</a>\n            </div>\n            :\n\n(¬1) في \"ل\": \"يطلق\".\n\n\n            <div class='pageno-container'>\n                <a class='pageno' href='#' id='v04p190'> Vol. 04, p. 190</a>\n            </div>\n            :\n\n(¬1) في النسخ: \"بالحمل\"، والصواب المثبت.\n\n\n            <div class='pageno-container'>\n                <a class='pageno' href='#' id='v04p191'> Vol. 04, p. 191</a>\n            </div>\n            :\n\n(¬1) في \"ل\": أي: \"بالأحوط\".\n\n\n            <div class='pageno-container'>\n                <a class='pageno' href='#' id='v04p199'> Vol. 04, p. 199</a>\n            </div>\n            :\n\n(¬1) زيادة يقتضيها السياق.\n\n\n            <div class='pageno-container'>\n                <a class='pageno' href='#' id='v04p203'> Vol. 04, p. 203</a>\n            </div>\n            :\n\n(¬1) القفيز: مكيال كان يكال به قديما، ويختلف مقداره في البلاد، ويعادل بالتقدير المصري الحديث نحو ستة عشر كيلو غراما.\nو(القفير) في المساحة قدر مئة وأربع وأربعين ذراعا. انظر: \"المعجم الوسيط\" (مادة: قفز).\n\n\n            <div class='pageno-container'>\n                <a class='pageno' href='#' id='v04p209'> Vol. 04, p. 209</a>\n            </div>\n            :\n\n(¬1) في \"ل\": \"يقبل\".\n\n\n            <div class='pageno-container'>\n                <a class='pageno' href='#' id='v04p211'> Vol. 04, p. 211</a>\n            </div>\n            :\n\n(¬1) في \"ل\": \"يكتسبه\".\n\n\n            <div class='pageno-container'>\n                <a class='pageno' href='#' id='v04p212'> Vol. 04, p. 212</a>\n            </div>\n            :\n\n(¬1) في \"ل\": \"يثبت\".\n\n\n            <div class='pageno-container'>\n                <a class='pageno' href='#' id='v04p217'> Vol. 04, p. 217</a>\n            </div>\n            :\n\n(¬1) جملة (أمر) صفة لقوله: \"وصية\"، وليست جواب الشرط، بل جواب الشرط \"قبل\".\n\n\n            <div class='pageno-container'>\n                <a class='pageno' href='#' id='v04p220'> Vol. 04, p. 220</a>\n            </div>\n            :\n\n(¬1) أي: غريبا فينا خامل الذكر ولا نعرف لولادته تاريخا. انظر: \"نهاية المطلب\" (7/ 100).\n\n\n            <div class='pageno-container'>\n                <a class='pageno' href='#' id='v04p224'> Vol. 04, p. 224</a>\n            </div>\n            :\n\n(¬1) في \"م\": \"يلتقيان\"، والمثبت موافق لما في \"نهاية المطلب\" (7/ 108).\n(¬2) في النسخ: \"على\"، والمثبت من \"نهاية المطلب\" (7/ 108).\n\n\n            <div class='pageno-container'>\n                <a class='pageno' href='#' id='v04p230'> Vol. 04, p. 230</a>\n            </div>\n            :\n\n(¬1) في \"ل\": \"أحكامه\".\n(¬2) في \"ل\": \"يثبت\".\n\n\n            <div class='pageno-container'>\n                <a class='pageno' href='#' id='v04p238'> Vol. 04, p. 238</a>\n            </div>\n            :\n\n(¬1) بعدها في \"ل\": \"على الأصح\"، وليست في \"نهاية المطلب\" (7/ 140).\n(¬2) أي: أعياه الطريق. انظر: \"الوسيط\" للغزالي (3/ 371).\n\n\n            <div class='pageno-container'>\n                <a class='pageno' href='#' id='v04p254'> Vol. 04, p. 254</a>\n            </div>\n            :\n\n(¬1) في \"ل\": \"فيمن\".\n\n\n            <div class='pageno-container'>\n                <a class='pageno' href='#' id='v04p261'> Vol. 04, p. 261</a>\n            </div>\n            :\n\n(¬1) الدق بكسر الدال: داء يصيب القلب، ولا يمتد معه حياة غالبا. انظر: \"أسنى المطالب\" لزكريا الأنصاري (3/ 38).\n\n\n            <div class='pageno-container'>\n                <a class='pageno' href='#' id='v04p264'> Vol. 04, p. 264</a>\n            </div>\n            :\n\n(¬1) وثمة وجه لم يذكره المصنف، وهو أن تكون جاهلة ويكون الواطئ عالما بالتحريم، فعند ذلك يجب المهر كما لو كانت مستكرهة. انظر: \"نهاية المطلب\" (7/ 207).\n\n\n            <div class='pageno-container'>\n                <a class='pageno' href='#' id='v04p266'> Vol. 04, p. 266</a>\n            </div>\n            :\n\n(¬1) في \"م\": \"لم يرجع ما غرم\".\n\n\n            <div class='pageno-container'>\n                <a class='pageno' href='#' id='v04p267'> Vol. 04, p. 267</a>\n            </div>\n            :\n\n(¬1) في \"ل\": \"وتقابضا\".\n\n\n            <div class='pageno-container'>\n                <a class='pageno' href='#' id='v04p269'> Vol. 04, p. 269</a>\n            </div>\n            :\n\n(¬1) أي: من المجني عليه الأول والمجني عليه الثاني.\n\n\n            <div class='pageno-container'>\n                <a class='pageno' href='#' id='v04p270'> Vol. 04, p. 270</a>\n            </div>\n            :\n\n(¬1) أي: المجني عليه الأول.\n(¬2) في \"ل\": \"يختص\".\n\n\n            <div class='pageno-container'>\n                <a class='pageno' href='#' id='v04p279'> Vol. 04, p. 279</a>\n            </div>\n            :\n\n(¬1) في \"ل\": \"لم نشترط\".\n\n\n            <div class='pageno-container'>\n                <a class='pageno' href='#' id='v04p283'> Vol. 04, p. 283</a>\n            </div>\n            :\n\n(¬1) الساجة: الخشبة المنحوتة المهياة للأساس، والساج ضرب عظيم من الشجر لا ينبت إلا بالهند، ويجلب منها إلى غيرها، ولا تكاد الأرض تبليه. انظر: \"المغرب\" للمطرزي (ما دة: سوج)، و\"المصباح المنير\" للفيومي (مادة: سوج).\n\n\n            <div class='pageno-container'>\n                <a class='pageno' href='#' id='v04p288'> Vol. 04, p. 288</a>\n            </div>\n            :\n\n(¬1) من \"نهاية <span id='ms1690'></span> المطلب\" (7/ 289).\n\n\n            <div class='pageno-container'>\n                <a class='pageno' href='#' id='v04p289'> Vol. 04, p. 289</a>\n            </div>\n            :\n\n(¬1) في \"ل\": \"كذباه\".\n\n\n            <div class='pageno-container'>\n                <a class='pageno' href='#' id='v04p290'> Vol. 04, p. 290</a>\n            </div>\n            :\n\n(¬1) البربط كجعفر: العود، قيل: هو معرب: بربط؛ أي: صدر الإوز، وبر بالفارسية الصدر؛ لأنه يشبهه. انظر: \"تاج العروس\" للزبيدي (مادة: بربط).\n\n\n            <div class='pageno-container'>\n                <a class='pageno' href='#' id='v04p292'> Vol. 04, p. 292</a>\n            </div>\n            :\n\n(¬1) في \"ل\": \"للطعام\".\n\n\n            <div class='pageno-container'>\n                <a class='pageno' href='#' id='v04p297'> Vol. 04, p. 297</a>\n            </div>\n            :\n\n(¬1) في \"ل\": \"لا ينقسم\".\n\n\n            <div class='pageno-container'>\n                <a class='pageno' href='#' id='v04p298'> Vol. 04, p. 298</a>\n            </div>\n            :\n\n(¬1) في \"ل\": \"ببذل ثمنه\".\n\n\n            <div class='pageno-container'>\n                <a class='pageno' href='#' id='v04p304'> Vol. 04, p. 304</a>\n            </div>\n            :\n\n(¬1) في \"ل\": \"يكفي\".\n\n\n            <div class='pageno-container'>\n                <a class='pageno' href='#' id='v04p305'> Vol. 04, p. 305</a>\n            </div>\n            :\n\n(¬1) في \"ل\": \"فالأصح أن لا يشترط\".\n(¬2) في \"ل\": \"يشترطه\".\n(¬3) في \"ل\": \"أو الإشهاد وتأخر أداء الثمن فللمشتري نقضه قولا واحدا وللشفيع نقضه على ... \"، والمثبت أقرب لعبارة \"نهاية المطلب\" (7/ 336).\n\n\n            <div class='pageno-container'>\n                <a class='pageno' href='#' id='v04p306'> Vol. 04, p. 306</a>\n            </div>\n            :\n\n(¬1) في \"م\": \"وأنكر الشفيع الشراء حلفا\"، والمثبت موافق لما في \"نهاية المطلب\" (7/ 338).\n\n\n            <div class='pageno-container'>\n                <a class='pageno' href='#' id='v04p308'> Vol. 04, p. 308</a>\n            </div>\n            :\n\n(¬1) في \"ل\": \"نشترطهما\".\n\n\n            <div class='pageno-container'>\n                <a class='pageno' href='#' id='v04p309'> Vol. 04, p. 309</a>\n            </div>\n            :\n\n(¬1) في \"ل\": \"نصيبه لزيد\".\n\n\n            <div class='pageno-container'>\n                <a class='pageno' href='#' id='v04p312'> Vol. 04, p. 312</a>\n            </div>\n            :\n\n(¬1) من \"نهاية المطلب\" (7/ 365).\n\n\n            <div class='pageno-container'>\n                <a class='pageno' href='#' id='v04p315'> Vol. 04, p. 315</a>\n            </div>\n            :\n\n(¬1) الودي: صغار الفسيل. انظر: \"تاج العروس\" للزبيدي (مادة: ودي).\n(¬2) \"أو أبرها\" من \"ل\".\n\n\n            <div class='pageno-container'>\n                <a class='pageno' href='#' id='v04p324'> Vol. 04, p. 324</a>\n            </div>\n            :\n\n(¬1) من \"نهاية المطلب\" (7/ 410).\n(¬2) في \"ل\" و\"م\": \"شقصا\"، والمثبت من \"نهاية المطلب\" (7/ 411).\n(¬3) في \"ل\": \"أخذ أحد النصيبين\"، ولم تجود في \"م\"، والمثبت من \"نهاية المطلب\" (7/ 411).\n\n\n            <div class='pageno-container'>\n                <a class='pageno' href='#' id='v04p328'> Vol. 04, p. 328</a>\n            </div>\n            :\n\n(¬1) أي: بطريق ثبوت الأقارير في مجالس القضاة. انظر: \"نهاية المطلب\" (7/ 422).\n(¬2) في \"ل\": \"بذل\".\n\n\n            <div class='pageno-container'>\n                <a class='pageno' href='#' id='v04p329'> Vol. 04, p. 329</a>\n            </div>\n            :\n\n(¬1) \"للوالد\": من \"ل\".\n\n\n            <div class='pageno-container'>\n                <a class='pageno' href='#' id='v04p331'> Vol. 04, p. 331</a>\n            </div>\n            :\n\n(¬1) في \"ل\": \"قيمته\".\n(¬2) هنا ينتهي المجلد الثاني من \"ل\"، وجاء فيها: \"والحمد لله وحده وصلواته على سيدنا محمد وآله وصحبه وسلم؛ كتبه مؤلفه على ما نقلوا عنه الثقات، وإنه إن شاء الله تعالى يغني عن غيره، نفع الله به كاتبه وقارئه، وكان الفراغ منه بحمد الله وعونه في ثامن عشر من شعبان من سنة خمس وأربعين وست مئة\".\n\n\n            <div class='pageno-container'>\n                <a class='pageno' href='#' id='v04p335'> Vol. 04, p. 335</a>\n            </div>\n            :\n\n(¬1) النقرة: القطعة المذابة من الفضة. انظر: \"المصباح المنير\" للفيومي (مادة: نقر).\n(¬2) كذا في الأصل؛ ومثله في نسخة من \"نهاية المطلب\"، وفي نسخة أثبتها =\n\n\n            <div class='pageno-container'>\n                <a class='pageno' href='#' id='v04p336'> Vol. 04, p. 336</a>\n            </div>\n            :\n\n= المحقق: \"حرزها\"؛ أي: صيانتها.\n\n\n            <div class='pageno-container'>\n                <a class='pageno' href='#' id='v04p337'> Vol. 04, p. 337</a>\n            </div>\n            :\n\n(¬1) في \"م\": \"الثاني\"، والمثبت من \"نهاية المطلب\" (7/ 449)، وهو الصواب.\n(¬2) في \"م\": \"الثالث\"، والمثبت من \"نهاية المطلب\" (7/ 451)، وهو الصواب.\n\n\n            <div class='pageno-container'>\n                <a class='pageno' href='#' id='v04p354'> Vol. 04, p. 354</a>\n            </div>\n            :\n\n(¬1) البراح: المتسع من الأرض. انظر: \"القاموس المحيط\" للفيروز أبادي (مادة: برح).\n\n\n            <div class='pageno-container'>\n                <a class='pageno' href='#' id='v04p358'> Vol. 04, p. 358</a>\n            </div>\n            :\n\n(¬1) في الأصل و\"ظ\": \"لما\"، والمثبت من \"نهاية المطلب\" (15/ 369).\n(¬2) من \"نهاية المطلب\" (10/ 380).\n\n\n            <div class='pageno-container'>\n                <a class='pageno' href='#' id='v04p359'> Vol. 04, p. 359</a>\n            </div>\n            :\n\n(¬1) الكر: مكيال لأهل العراق، أو ستون قفيزا، أو أربعون إردبا، وطالما كان الخلاف في الإردب أنه (90) أو (198) ليترا، يبقى هذا المكيال مجهول التحديد على وجه التحقيق. انظر: \"البيان\" للعمراني (الفهارس العامة <span id='ms1691'></span>) (ص: 505)، و \"المعجم الوسيط\" (مادة: كرر). وحسبه الأزهري أنه: اثنا عشر وسقا؛ والوسق عند الشافعي (130) كغ، ويعادل (60) صاعا، وهو حمل بعير، وعليه فإن (الكر) يعادل: (1560) كغ. انظر: \"المصباح المنير\" (مادة: كرر)، وفهارس \"البيان\".\n\n\n            <div class='pageno-container'>\n                <a class='pageno' href='#' id='v04p362'> Vol. 04, p. 362</a>\n            </div>\n            :\n\n(¬1) هو أبو منصور عبد القاهر بن طاهر التميمي البغدادي، شيخ إمام الحرمين في الفرائض، وعلامة العالم في الفرائض والحساب والكلام والمقدرات والفقه وأصوله، توفي سنة: 429 ه. ترجمته في \"تهذيب الأسماء واللغات\" (2/ 268)، و\"طبقات الشافعية الكبرى\" (5/ 136).\n\n\n            <div class='pageno-container'>\n                <a class='pageno' href='#' id='v04p363'> Vol. 04, p. 363</a>\n            </div>\n            :\n\n(¬1) لعل الأنسب بالسياق: \"نتبين\".\n\n\n            <div class='pageno-container'>\n                <a class='pageno' href='#' id='v04p371'> Vol. 04, p. 371</a>\n            </div>\n            :\n\n(¬1) في \"نهاية المطلب\" (11/ 60): \"ضعفوا له ضعف نصيب أحد ولدي\".\n\n\n            <div class='pageno-container'>\n                <a class='pageno' href='#' id='v04p373'> Vol. 04, p. 373</a>\n            </div>\n            :\n\n(¬1) في \"ظ\": \"صرف\"، والمثبت من \"نهاية المطلب\" (11/ 66)، وهو الصواب.\n\n\n            <div class='pageno-container'>\n                <a class='pageno' href='#' id='v04p374'> Vol. 04, p. 374</a>\n            </div>\n            :\n\n(¬1) أي: فتبلغ تسعة، وكذا في كل ما سيأتي على هذا النحو.\n\n\n            <div class='pageno-container'>\n                <a class='pageno' href='#' id='v04p376'> Vol. 04, p. 376</a>\n            </div>\n            :\n\n(¬1) في \"ظ\": \"وعشرين\"، والصواب المثبت.\n\n\n            <div class='pageno-container'>\n                <a class='pageno' href='#' id='v04p382'> Vol. 04, p. 382</a>\n            </div>\n            :\n\n(¬1) في \"ظ\": \"إذا كان له\"، والمثبت موافق لما في \"نهاية المطلب\" (11/ 78)، مغنيه: \"فإنه كان له ... \".\n(¬2) كذا وقعت العبارة في \"ظ\"، والذي في \"نهاية المطلب\" (11/ 79): \"وقد بقي لصاحب الربع إلى تمام الربع سبعة أسهم\".\n\n\n            <div class='pageno-container'>\n                <a class='pageno' href='#' id='v04p386'> Vol. 04, p. 386</a>\n            </div>\n            :\n\n(¬1) في \"ظ\": \"وثلثان\"، والصواب المثبت.\n\n\n            <div class='pageno-container'>\n                <a class='pageno' href='#' id='v04p387'> Vol. 04, p. 387</a>\n            </div>\n            :\n\n(¬1) في \"ظ\": \"يرده\"، والصواب المثبت.\n\n\n            <div class='pageno-container'>\n                <a class='pageno' href='#' id='v04p401'> Vol. 04, p. 401</a>\n            </div>\n            :\n\n(¬1) أي: بالموصى بمنافعه.\n(¬2) أي: إذا وطئ الوارث الجارية الموصى بمنفعتها وأولدها، صارت أم ولد له.\n\n\n            <div class='pageno-container'>\n                <a class='pageno' href='#' id='v04p409'> Vol. 04, p. 409</a>\n            </div>\n            :\n\n(¬1) الكوبة: الطبل الصغير المخصر، والبربط كجعفر: العود، وكلاهما معرب. انظر: \"المصباح المنير اللفيومي (مادة: كوب وبربط).\n\n\n            <div class='pageno-container'>\n                <a class='pageno' href='#' id='v04p410'> Vol. 04, p. 410</a>\n            </div>\n            :\n\n(¬1) جمع النيزك كحيدر، فارسي معرب، وهو الرمح القصير. كما في \"المصباح المنير\" للفيومي (مادة: نزك).\n\n\n            <div class='pageno-container'>\n                <a class='pageno' href='#' id='v04p411'> Vol. 04, p. 411</a>\n            </div>\n            :\n\n(¬1) في \"ظ\": \"مركب\"، والصواب المثبت.\n\n\n            <div class='pageno-container'>\n                <a class='pageno' href='#' id='v04p412'> Vol. 04, p. 412</a>\n            </div>\n            :\n\n(¬1) في \"ظ\": \"فالقدر\"، والصواب المثبت.\n\n\n            <div class='pageno-container'>\n                <a class='pageno' href='#' id='v04p416'> Vol. 04, p. 416</a>\n            </div>\n            :\n\n(¬1) في \"نهاية المطلب\" (11/ 204): \"بالأعزار والأخطار\".\n\n\n            <div class='pageno-container'>\n                <a class='pageno' href='#' id='v04p422'> Vol. 04, p. 422</a>\n            </div>\n            :\n\n(¬1) أي في الزائد على الثلث. انظر: \"نهاية المطلب\" (11/ 230).\n(¬2) أي: يفي ثلثه بتمام الثلث الموصى به. المرجع السابق، الموضع نفسه.\n\n\n            <div class='pageno-container'>\n                <a class='pageno' href='#' id='v04p423'> Vol. 04, p. 423</a>\n            </div>\n            :\n\n(¬1) بسقت النخلة (بسوقا): طالت؛ فهي (باسقة). \"المصباح المنير\" (مادة: بسق).\n\n\n            <div class='pageno-container'>\n                <a class='pageno' href='#' id='v04p428'> Vol. 04, p. 428</a>\n            </div>\n            :\n\n(¬1) ما بين معكوفتين مستفاد من \"نهاية المطلب\" (11/ 252).\n\n\n            <div class='pageno-container'>\n                <a class='pageno' href='#' id='v04p432'> Vol. 04, p. 432</a>\n            </div>\n            :\n\n(¬1) في \"ظ\": \"ويرق\" بدل: \"ثم يرق\"، والمثبت من \"نهاية المطلب\" (11/ 266).\n\n\n            <div class='pageno-container'>\n                <a class='pageno' href='#' id='v04p435'> Vol. 04, p. 435</a>\n            </div>\n            :\n\n(¬1) أخرجه مسلم (1631)، من حديث أبي هريرة - رضي الله عنه -.\n\n\n            <div class='pageno-container'>\n                <a class='pageno' href='#' id='v04p442'> Vol. 04, p. 442</a>\n            </div>\n            :\n\n(¬1) وليس هذا بصحيح، كما بينه شيخ الإسلام ابن تيمية في كتاب \"الجواب الباهر في زوار المقابر\". (الناشر).\n\n\n            <div class='pageno-container'>\n                <a class='pageno' href='#' id='v04p443'> Vol. 04, p. 443</a>\n            </div>\n            :\n\n(¬1) في الأصل: \"ويختص\"، والصواب المثبت. انظر: \"نهاية المطلب\" (11/ 350).\n(¬2) \"كما ذكرناه في العلوية\" يقابلها في \"نهاية المطلب\" (11/ 350): \"حتى تكون <span id='ms1692'></span> وصيته لقرابته كوصيته للعلوية\". وبها يظهر المراد.\n(¬3) في \"ظ\": \"إلى البطن العال إلى الشافعي\"، والمثبت من المصدر المذكور.\n\n\n            <div class='pageno-container'>\n                <a class='pageno' href='#' id='v04p446'> Vol. 04, p. 446</a>\n            </div>\n            :\n\n(¬1) في \"ظ\": \"الذي\"، والصواب المثبت.\n\n\n            <div class='pageno-container'>\n                <a class='pageno' href='#' id='v04p449'> Vol. 04, p. 449</a>\n            </div>\n            :\n\n(¬1) أبو ثور: هو إبراهيم بن خالد، قال ابن حبان: أحد أئمة الدنيا فقها وعلما وورعا.\nكان على مذهب أبي حنيفة، فلما قدم الشافعي بغداد تبعه، قال عنه الرافعي: له مذهب مستقل، وقال النووي: اتفقوا على توثيقه وجلالته، من مصنفاته الكثيرة كتاب \"ذكر فيه اختلاف مالك والشافعي\" وذكر فيه مذهبه، توفي سنة (240 ه).\n\n\n            <div class='pageno-container'>\n                <a class='pageno' href='#' id='v04p450'> Vol. 04, p. 450</a>\n            </div>\n            :\n\n(¬1) في \"ظ\": \"روجع\"، والمثبت هو الأنسب بالسياق. انظر: \"نهاية المطلب\" (11/ 322).\n\n\n            <div class='pageno-container'>\n                <a class='pageno' href='#' id='v04p451'> Vol. 04, p. 451</a>\n            </div>\n            :\n\n(¬1) في \"ظ\": \"الحيالات\"، والمثبت من \"نهاية المطلب\" (11/ 322).\n\n\n            <div class='pageno-container'>\n                <a class='pageno' href='#' id='v04p454'> Vol. 04, p. 454</a>\n            </div>\n            :\n\n(¬1) زيادة من \"نهاية المطلب\" (11/ 330).\n\n\n            <div class='pageno-container'>\n                <a class='pageno' href='#' id='v04p457'> Vol. 04, p. 457</a>\n            </div>\n            :\n\n(¬1) في \"ظ\": \"لا\"، بدل: \"لأنه\"، والصواب المثبت. انظر: \"نهاية المطلب\" (11/ 338).\n\n\n            <div class='pageno-container'>\n                <a class='pageno' href='#' id='v04p459'> Vol. 04, p. 459</a>\n            </div>\n            :\n\n(¬1) في \"ظ\": \"الغبطة\"، والمثبت من \"نهاية المطلب\" (11/ 340)، وهو الأنسب بسياق الكلام.\n(¬2) والبرسام: ورم حار يعرض للحجاب الذي بين الكبد والأمعاء، ثم يتصل بالدماغ. انظر: \"تاج العروس\" للزبيدي (مادة: برسم).\n\n\n            <div class='pageno-container'>\n                <a class='pageno' href='#' id='v04p461'> Vol. 04, p. 461</a>\n            </div>\n            :\n\n(¬1) بعد هذه الكلمة في \"ظ\" بياض بمقدار ثلاثة أسطر ونصف تقريبا، أما في \"نهاية المطلب\" فقد اكتفى الإمام الجويني إثر هذا السؤال بقوله: \"هذا منه تردد وقد قدمته\". انظر: \"نهاية المطلب\" (11/ 342 - 343)، وانظر كذلك ما تقدم في بداية هذا الباب وخصوصا قوله: \"وإذا ترتب الموت على مرض غير مخوف فإن قطع أهل البصر. . .\".\n\n\n            <div class='pageno-container'>\n                <a class='pageno' href='#' id='v04p463'> Vol. 04, p. 463</a>\n            </div>\n            :\n\n(¬1) أي: من لزمته كفارة الظهار.\n\n\n            <div class='pageno-container'>\n                <a class='pageno' href='#' id='v04p464'> Vol. 04, p. 464</a>\n            </div>\n            :\n\n(¬1) هذا القول فيه دلالة على منهجية الإمام العز رحمه الله في اختصار الكتاب؛ بأنه استوعب في هذا المختصر مسائل كتاب \"نهاية المطلب\" الكتاب الأصل المختصر، وأهمل هذه المسائل التي استوعبت جل الجزء العاشر من كتاب الجويني، وهي جديرة بالدراسة من قبل مؤرخي علم الرياضيات من المعاصرين.\n\n\n            <div class='pageno-container'>\n                <a class='pageno' href='#' id='v04p465'> Vol. 04, p. 465</a>\n            </div>\n            :\n\n(¬1) أي: لعل الصواب: \"ويصح إيصاء\". انظر: \"نهاية المطلب\" (11/ 52).\n\n\n            <div class='pageno-container'>\n                <a class='pageno' href='#' id='v04p467'> Vol. 04, p. 467</a>\n            </div>\n            :\n\n(¬1) يعني: \"إذا أوصى لمعينين، ونفذت الوصايا باتساع الثلث وقبول الموصى لهم، فلا يكاد يظهر للوصي أثر. انظر: \"نهاية المطلب\" (11/ 355).\n\n\n            <div class='pageno-container'>\n                <a class='pageno' href='#' id='v04p470'> Vol. 04, p. 470</a>\n            </div>\n            :\n\n(¬1) في \"ظ\": \"على يسر\"، وكذا في نسخة من \"نهاية المطلب\" أشار إليها محققه.\nانظر: \"نهاية المطلب\" (11/ 367).\n\n\n            <div class='pageno-container'>\n                <a class='pageno' href='#' id='v04p472'> Vol. 04, p. 472</a>\n            </div>\n            ",
  "pages": [
    "007",
    "009",
    "010",
    "014",
    "015",
    "016",
    "018",
    "021",
    "023",
    "025",
    "027",
    "029",
    "031",
    "034",
    "035",
    "037",
    "038",
    "039",
    "041",
    "049",
    "054",
    "055",
    "066",
    "069",
    "070",
    "071",
    "072",
    "073",
    "074",
    "076",
    "077",
    "081",
    "085",
    "103",
    "105",
    "108",
    "113",
    "134",
    "137",
    "143",
    "151",
    "158",
    "161",
    "163",
    "164",
    "166",
    "170",
    "174",
    "175",
    "180",
    "184",
    "190",
    "191",
    "199",
    "203",
    "209",
    "211",
    "212",
    "217",
    "220",
    "224",
    "230",
    "238",
    "254",
    "261",
    "264",
    "266",
    "267",
    "269",
    "270",
    "279",
    "283",
    "288",
    "289",
    "290",
    "292",
    "297",
    "298",
    "304",
    "305",
    "306",
    "308",
    "309",
    "312",
    "315",
    "324",
    "328",
    "329",
    "331",
    "335",
    "336",
    "337",
    "354",
    "358",
    "359",
    "362",
    "363",
    "371",
    "373",
    "374",
    "376",
    "382",
    "386",
    "387",
    "401",
    "409",
    "410",
    "411",
    "412",
    "416",
    "422",
    "423",
    "428",
    "432",
    "435",
    "442",
    "443",
    "446",
    "449",
    "450",
    "451",
    "454",
    "457",
    "459",
    "461",
    "463",
    "464",
    "465",
    "467",
    "470",
    "472"
  ],
  "volumes": [
    "01",
    "02",
    "03",
    "04",
    "05",
    "06",
    "07",
    "08"
  ]
}